<?xml version="1.0" encoding="UTF-8"?>
<!DOCTYPE hibernate-mapping PUBLIC "-//Hibernate/Hibernate Mapping DTD 3.0//EN" "http://hibernate.sourceforge.net/hibernate-mapping-3.0.dtd">
<hibernate-mapping package="org.motechproject.mobile.core.model">
  <union-subclass extends="MotechEntityImpl" name="IncomingMessageImpl" table="incoming_message">
    <many-to-one class="IncomingMessageSessionImpl" column="incoming_message_session_id" name="incomingMsgSession"/>
    <many-to-one cascade="all" class="IncomingMessageFormImpl" column="incoming_message_form_id" name="incomingMessageForm"/>
    <many-to-one cascade="all" class="IncomingMessageResponseImpl" column="incoming_message_response_id" name="incomingMessageResponse" unique="true"/>
    <property column="message_content" length="700" name="content" type="string"/>
    <property column="date_created" name="dateCreated" type="timestamp"/>
    <property generated="always" insert="false" name="lastModified" update="false">
      <column default="current_timestamp" name="last_modified" sql-type="timestamp"/>
    </property>
    <property access="field" column="message_status" name="messageStatus" type="incMessageStatus"/>
  </union-subclass>
</hibernate-mapping>
